[
  {
    "id": "se_081",
    "text": "介護保険の「地域密着型サービス」に含まれないものを1つ選びなさい。",
    "options": [
      "認知症対応型共同生活介護（グループホーム）",
      "小規模多機能型居宅介護",
      "定期巡回・随時対応型訪問介護看護",
      "訪問看護"
    ],
    "correctIndex": 3,
    "explanation": "訪問看護は「居宅サービス」に分類されます。1〜3は住み慣れた地域での生活を支える「地域密着型サービス」です。",
    "subject": "elderly_care",
    "difficulty": "B",
    "isEnabled": true
  },
  {
    "id": "se_082",
    "text": "「介護老人福祉法（特別養護老人ホーム）」の入所要件として、原則として定められている要介護状態はどれか。",
    "options": [
      "要支援1以上",
      "要介護1以上",
      "要介護3以上",
      "要介護5のみ"
    ],
    "correctIndex": 2,
    "explanation": "2015年の改正により、新規入所は原則として「要介護3以上」の高齢者に限定されました（やむを得ない事情がある場合を除く）。",
    "subject": "elderly_care",
    "difficulty": "A",
    "isEnabled": true
  },
  {
    "id": "se_083",
    "text": "「障害者総合支援法」の「自立支援医療」の対象に含まれないものはどれか。",
    "options": [
      "精神通院医療",
      "更生医療",
      "育成医療",
      "救急医療"
    ],
    "correctIndex": 3,
    "explanation": "自立支援医療には、精神疾患の「精神通院」、身体障害の軽減を図る「更生（18歳以上）」「育成（18歳未満）」の3つがあります。",
    "subject": "disability_service",
    "difficulty": "B",
    "isEnabled": true
  },
  {
    "id": "se_084",
    "text": "「就労継続支援B型」の説明として、最も適切なものを1つ選びなさい。",
    "options": [
      "一般企業での就労を希望し、2年以内の就職を目指す支援。",
      "雇用契約を締結し、最低賃金以上の給料を支払いながら働く支援。",
      "雇用契約を締結せず、作業の対価として「工賃」を支払う支援。",
      "就職後6ヶ月間、職場定着のために相談に乗る支援。"
    ],
    "correctIndex": 2,
    "explanation": "B型は、年齢や体力的に雇用契約が難しい人を対象に、無理のない範囲で活動し「工賃」を得る支援です。1は移行支援、2はA型、4は定着支援です。",
    "subject": "disability_service",
    "difficulty": "B",
    "isEnabled": true
  },
  {
    "id": "se_085",
    "text": "「児童虐待の防止等に関する法律」において、保護者が児童を車内に放置して立ち去る行為は何に該当するか。",
    "options": [
      "ネグレクト（養育の放棄・怠慢）",
      "身体的虐待",
      "心理的虐待",
      "性的虐待"
    ],
    "correctIndex": 0,
    "explanation": "食事を与えない、不潔な環境に置く、車内放置、学校に行かせないなどは「ネグレクト」に該当します。",
    "subject": "child_welfare",
    "difficulty": "A",
    "isEnabled": true
  },
  {
    "id": "se_086",
    "text": "「児童福祉法」に基づく「放課後等デイサービス」の主な対象者はどれか。",
    "options": [
      "保育所に通う乳幼児",
      "学校教育法に規定する学校に就学している障害児",
      "不登校の中学生",
      "非行を犯した少年"
    ],
    "correctIndex": 1,
    "explanation": "障害のある学童に対し、授業終了後や夏休みに、生活能力向上のための訓練や交流の場を提供するサービスです。",
    "subject": "child_welfare",
    "difficulty": "B",
    "isEnabled": true
  },
  {
    "id": "se_087",
    "text": "生活保護の「出産扶助」の支給方法として、正しいものを1つ選びなさい。",
    "options": [
      "現物給付（病院での出産そのものを提供）",
      "現金給付（定められた基準額を世帯に支給）",
      "貸付（後で返済が必要）",
      "支給されない"
    ],
    "correctIndex": 1,
    "explanation": "出産扶助と葬祭扶助は、原則として「現金給付」で行われます。医療扶助と介護扶助は原則「現物給付」です。",
    "subject": "public_assistance",
    "difficulty": "B",
    "isEnabled": true
  },
  {
    "id": "se_088",
    "text": "「生活困窮者自立支援法」に基づき、すべての福祉事務所設置自治体に設置が義務付けられている事業はどれか。",
    "options": [
      "就労準備支援事業",
      "家計改善支援事業",
      "自立相談支援事業",
      "一時生活支援事業"
    ],
    "correctIndex": 2,
    "explanation": "自立相談支援事業と住居確保給付金の支給は「必須事業」です。その他（就労準備、家計改善等）は「任意事業」です。",
    "subject": "public_assistance",
    "difficulty": "B",
    "isEnabled": true
  },
  {
    "id": "se_089",
    "text": "介護保険の「地域包括支援センター」に必ず配置すべき3つの専門職に含まれないものはどれか。",
    "options": [
      "保健師（または看護師）",
      "主任介護支援専門員",
      "社会福祉士",
      "理学療法士"
    ],
    "correctIndex": 3,
    "explanation": "地域包括には、保健師、主任ケアマネ、社会福祉士の3職種が配置され、包括的・継続的な支援を行います。",
    "subject": "elderly_care",
    "difficulty": "A",
    "isEnabled": true
  },
  {
    "id": "se_090",
    "text": "「障害者総合支援法」における「同行援護」の主な対象者は誰か。",
    "options": [
      "肢体不自由により外出困難な者",
      "視覚障害により外出困難な者",
      "重度の知的障害により行動が危険な者",
      "難病により常に介護が必要な者"
    ],
    "correctIndex": 1,
    "explanation": "視覚障害者の外出に同行し、移動の援護や情報の提供を行うサービスが「同行援護」です。肢体不自由は「移動支援（地域生活支援事業）」などになります。",
    "subject": "disability_service",
    "difficulty": "B",
    "isEnabled": true
  },
  {
    "id": "se_091",
    "text": "児童相談所の設置義務がある自治体として、正しいものを1つ選びなさい。",
    "options": [
      "すべての市町村",
      "すべての都道府県および政令指定都市",
      "人口10万人以上の都市",
      "一部の過疎地域のみ"
    ],
    "correctIndex": 1,
    "explanation": "都道府県と政令指定都市には設置義務があります。中核市や特別区は「設置できる（任意）」とされています。",
    "subject": "child_welfare",
    "difficulty": "B",
    "isEnabled": true
  },
  {
    "id": "se_092",
    "text": "「介護予防・日常生活支援総合事業（新しい総合事業）」の実施主体はどこか。",
    "options": [
      "国",
      "都道府県",
      "市町村",
      "厚生労働省"
    ],
    "correctIndex": 2,
    "explanation": "市町村が地域のニーズに合わせて柔軟に実施する事業です。要支援者や65歳以上の全ての人が対象となり得ます。",
    "subject": "elderly_care",
    "difficulty": "A",
    "isEnabled": true
  },
  {
    "id": "se_093",
    "text": "生活保護の「生活扶助」の「第1類」が対象とする、生活に必要な経費はどれか。",
    "options": [
      "個人の飲食や衣服等の個人的経費",
      "水道光熱費等の世帯共通の経費",
      "家賃や地代などの経費",
      "学用品や通学費などの経費"
    ],
    "correctIndex": 0,
    "explanation": "第1類は「個人的経費」、第2類は「世帯共通経費（光熱水費等）」です。家賃は住宅扶助、学用品は教育扶助です。",
    "subject": "public_assistance",
    "difficulty": "C",
    "isEnabled": true
  },
  {
    "id": "se_094",
    "text": "「身体障害者手帳」の等級（1級〜6級）において、最も重度の状態を示すのはどれか。",
    "options": [
      "1級",
      "3級",
      "6級",
      "10級"
    ],
    "correctIndex": 0,
    "explanation": "身体障害者手帳は1級が最も重く、数字が大きくなるほど軽くなります。7級は2つ以上の重複により手帳交付対象となります。",
    "subject": "disability_service",
    "difficulty": "A",
    "isEnabled": true
  },
  {
    "id": "se_095",
    "text": "「児童養護施設」の入所年齢として、原則的な上限はどれか。",
    "options": [
      "12歳（小学校卒業まで）",
      "15歳（中学校卒業まで）",
      "18歳（必要があれば22歳まで）",
      "25歳まで"
    ],
    "correctIndex": 2,
    "explanation": "原則18歳までですが、大学進学等のやむを得ない事情がある場合は、特例として22歳の年度末まで延長が可能です。",
    "subject": "child_welfare",
    "difficulty": "B",
    "isEnabled": true
  },
  {
    "id": "se_096",
    "text": "介護保険の「福祉用具貸与（レンタル）」の対象に含まれるもので、要介護1以下の人でも原則として利用可能なものはどれか。",
    "options": [
      "車いす",
      "特殊寝台（介護ベッド）",
      "床ずれ防止用具",
      "歩行器"
    ],
    "correctIndex": 3,
    "explanation": "車いすやベッド等は原則「要介護2以上」が対象ですが、歩行器、手すり（工事不要）、歩行補助つえ、スロープは「要支援・要介護1」でも利用可能です。",
    "subject": "elderly_care",
    "difficulty": "B",
    "isEnabled": true
  },
  {
    "id": "se_097",
    "text": "「障害者雇用促進法」に基づく「法定雇用率」において、2024年4月から民間企業に課せられた基準はどれか。",
    "options": [
      "1.8%",
      "2.2%",
      "2.5%",
      "3.0%"
    ],
    "correctIndex": 2,
    "explanation": "2024年4月から「2.5%」に引き上げられました。さらに2026年7月には「2.7%」への引き上げが予定されています。",
    "subject": "disability_service",
    "difficulty": "B",
    "isEnabled": true
  },
  {
    "id": "se_098",
    "text": "生活保護の「就労自立給付金」に関する説明として、正しいものを1つ選びなさい。",
    "options": [
      "保護費を貯金するための特別な手当である。",
      "就労により保護を廃止（または停止）された場合に、自立を助長するために一括支給される。",
      "就職が決まった直後に、スーツ代として支給される。",
      "ハローワークから支給される失業手当の一種である。"
    ],
    "correctIndex": 1,
    "explanation": "就労して経済的に自立し、保護を抜けることができた受給者に対し、安定した生活を支える目的で支給されます。",
    "subject": "public_assistance",
    "difficulty": "C",
    "isEnabled": true
  },
  {
    "id": "se_099",
    "text": "「保育所」と「幼稚園」の両方の機能を併せ持ち、地域の子育て支援も行う施設を何というか。",
    "options": [
      "乳児院",
      "認定こども園",
      "児童館",
      "子育て支援センター"
    ],
    "correctIndex": 1,
    "explanation": "保護者の就労状況に関わらず受け入れが可能で、幼児教育と保育を一体的に提供する施設です。",
    "subject": "child_welfare",
    "difficulty": "A",
    "isEnabled": true
  },
  {
    "id": "se_100",
    "text": "「重度訪問介護」の対象となる障害の程度として、正しいものを1つ選びなさい。",
    "options": [
      "障害支援区分1以上",
      "障害支援区分3以上",
      "障害支援区分4以上で、肢体不自由等の一定の要件を満たす者",
      "全盲の視覚障害者"
    ],
    "correctIndex": 2,
    "explanation": "重度の肢体不自由または知的・精神障害により、常時介護が必要な（区分4以上の）人が対象です。",
    "subject": "disability_service",
    "difficulty": "C",
    "isEnabled": true
  }
]
